FSM.v
module FSM (
    input car_in, //first bit of 4 bit input
    input [2:0] car_out, //three last bits of 4 bit input
    input clk,
    input rst,
    output reg [2:0] space_count, // 7 seg
    output reg [1:0] near_slot, // 7 seg
    output reg door_open,
    output reg door_open_exit,
    output reg full_garage,
    output reg [3:0] state
);

    parameter 
        empty = 4'b0000,
        s1 = 4'b0001, s2 = 4'b0010, s3 = 4'b0011, s4 = 4'b0100,
        s5 = 4'b0101, s6 = 4'b0110, s7 = 4'b0111, s8 = 4'b1000,
        s9 = 4'b1001, s10 = 4'b1010, s11 = 4'b1011, s12 = 4'b1100,
        s13 = 4'b1101, s14 = 4'b1110,
        full = 4'b1111;

    

    always @(posedge clk or posedge rst) 
    begin
        if(rst)
        begin
            state <= empty;
            full_garage <= 1'b0;
            space_count <= 3'b100;
            door_open <= 1'b0;
            door_open_exit <= 1'b0;
            near_slot <= 2'b00;
        end
        
        
        
        case (state)
            empty: 
            begin
                door_open <= 1'b0;
                door_open_exit = 1'b0;
                if (car_in) 
                begin
                    space_count <= 3'b011;
                    near_slot <= 2'b01;
                    door_open <= 1'b1;
                    state <= s1;
                end
            end
            s1: 
            begin
                door_open <= 1'b0;
                if (car_in) 
                begin
                    space_count <= 3'b010;
                    near_slot <= 2'b10;
                    door_open <= 1'b1;
                    state <= s3;
                end else if (car_out[2]) 
                begin
                    if (car_out[1:0] == 2'b00) 
                    begin
                        state <= empty;
                        space_count <= 3'b100;
                        near_slot <= 2'b00;
                        door_open_exit <= 1'b1;
                    end
                end
            end
            s2: 
            begin
                door_open <= 1'b0;
                door_open_exit = 1'b0;
                if (car_in) 
                begin
                    state <= s3;
                    space_count <= 3'b010;
                    near_slot <= 2'b10;
                    door_open <= 1'b1;
                end else if (car_out[2]) 
                begin
                    if (car_out[1:0] == 2'b01) 
                    begin
                        state <= empty;
                        space_count <= 3'b100;
                        near_slot <= 2'b00;
                        door_open_exit <= 1'b1;
                    end
                end
            end
            s3: 
            begin
                door_open <= 1'b0;
                if (car_in) 
                begin
                    state <= s7;
                    space_count <= 3'b001;
                    near_slot <= 2'b11;
                    door_open <= 1'b1;
                end else if (car_out[2]) 
                begin
                    if (car_out[1:0] == 2'b00) 
                    begin
                        state <= s2;
                        space_count <= 3'b011;
                        near_slot <= 2'b00;
                        door_open_exit <= 1'b1;
                    end else if (car_out[1:0] == 2'b01) 
                    begin
                        state <= s1;
                        space_count <= 3'b011;
                        near_slot <= 2'b01;
                        door_open_exit <= 1'b1;
                    end
                end
            end
            s4: 
            begin
                door_open <= 1'b0;
                door_open_exit = 1'b0;
                if (car_in) 
                begin
                    state <= s6;
                    space_count <= 3'b010;
                    near_slot <= 2'b00;
                    door_open <= 1'b1;
                end else if (car_out[2]) 
                begin
                    if (car_out[1:0] == 2'b10) 
                    begin
                        state <= empty;
                        space_count <= 3'b100;
                        near_slot <= 2'b00;
                        door_open_exit <= 1'b1;
                    end
                end
            end
            s5: 
            begin
                door_open <= 1'b0;
                door_open_exit = 1'b0;
                if (car_in) 
                begin
                    state <= s7;
                    space_count <= 3'b001;
                    near_slot <= 2'b11;
                    door_open <= 1'b1;
                end else if (car_out[2]) 
                begin
                    if (car_out[1:0] == 2'b00) 
                    begin
                        state <= s4;
                        space_count <= 3'b011;
                        near_slot <= 2'b00;
                        door_open_exit <= 1'b1;
                    end else if (car_out[1:0] == 2'b10) 
                    begin
                        state <= s1;
                        space_count <= 3'b011;
                        near_slot <= 2'b01;
                        door_open_exit <= 1'b1;
                    end
                end
            end
            s6: 
            begin
                door_open <= 1'b0;
                door_open_exit = 1'b0;
                if (car_in) 
                begin
                    state <= s7;
                    space_count <= 3'b001;
                    near_slot <= 2'b11;
                    door_open <= 1'b1;
                end else if (car_out[2]) 
                begin
                    if (car_out[1:0] == 2'b01) 
                    begin
                        state <= s4;
                        space_count <= 3'b011;
                        near_slot <= 2'b00;
                        door_open_exit <= 1'b1;
                    end else if (car_out[1:0] == 2'b10) 
                    begin
                        state <= s2;
                        space_count <= 3'b011;
                        near_slot <= 2'b00;
                        door_open_exit <= 1'b1;
                    end
                end
            end
            s7: 
            begin
                door_open <= 1'b0;
                door_open_exit = 1'b0;
                if (car_in) 
                begin
                    state <= full;
                    space_count <= 3'b000;
                    full_garage <= 1'b1;
                    door_open <= 1'b1;  //be carefull
                end else if (car_out[2]) 
                begin
                    if (car_out[1:0] == 2'b10) 
                    begin
                        state <= s3;
                        space_count <= 3'b010;
                        near_slot <= 2'b10;
                        door_open_exit <= 1'b1;
                    end else if (car_out[1:0] == 2'b01) 
                    begin
                        state <= s5;
                        space_count <= 3'b010;
                        near_slot <= 2'b01;
                        door_open_exit <= 1'b1;
                    end else if (car_out[1:0] == 2'b00) 
                    begin
                        state <= s6;
                        space_count <= 3'b010;
                        near_slot <= 2'b00;
                        door_open_exit <= 1'b1;
                    end
                end
            end
            s8: 
            begin
                door_open <= 1'b0;
                door_open_exit = 1'b0;
                if (car_in) 
                begin
                    state <= s9;
                    space_count <= 3'b010;
                    near_slot <= 2'b01;
                    door_open <= 1'b1;
                end else if (car_out[2]) 
                begin
                    if (car_out[1:0] == 2'b11) 
                    begin
                        state <= empty;
                        space_count <= 3'b100;
                        near_slot <= 2'b00;
                        door_open_exit <= 1'b1;
                    end
                end
            end
            s9: 
            begin
                door_open <= 1'b0;
                door_open_exit = 1'b0;
                if (car_in) 
                begin
                    state <= s11;
                    space_count <= 3'b001;
                    near_slot <= 2'b10;
                    door_open <= 1'b1;
                end else if (car_out[2]) 
                begin
                    if (car_out[1:0] == 2'b00) 
                    begin
                        state <= s8;
                        space_count <= 3'b011;
                        near_slot <= 2'b00;
                        door_open_exit <= 1'b1;
                    end else if (car_out[1:0] == 2'b11) 
                    begin
                        state <= s1;
                        space_count <= 3'b011;
                        near_slot <= 2'b01;
                        door_open_exit <= 1'b1;
                    end
                end
            end
            s10: 
            begin
                door_open <= 1'b0;
                door_open_exit = 1'b0;
                if (car_in) 
                begin
                    state <= s11;
                    space_count <= 3'b001;
                    near_slot <= 2'b10;
                    door_open <= 1'b1;
                end else if (car_out[2]) 
                begin
                    if (car_out[1:0] == 2'b01) 
                    begin
                        state <= s8;
                        space_count <= 3'b011;
                        near_slot <= 2'b00;
                        door_open_exit <= 1'b1;
                    end else if (car_out[1:0] == 2'b11) 
                    begin
                        state <= s2;
                        space_count <= 3'b011;
                        near_slot <= 2'b00;
                        door_open_exit <= 1'b1;
                    end
                end
            end
            s11: 
            begin
                door_open <= 1'b0;
                door_open_exit = 1'b0;
                if (car_in) 
                begin
                    state <= full;
                    full_garage <= 1'b1;
                    door_open <= 1'b1;
                end else if (car_out[2]) 
                begin
                    if (car_out[1:0] == 2'b00) 
                    begin
                        state <= s10;
                        space_count <= 3'b010;
                        near_slot <= 2'b00;
                        door_open_exit <= 1'b1;
                    end else if (car_out[1:0] == 2'b01) 
                    begin
                        state <= s9;
                        space_count <= 3'b010;
                        near_slot <= 2'b01;
                        door_open_exit <= 1'b1;
                    end else if (car_out[1:0] == 2'b11) 
                    begin  // be carefull
                        state <= s3;
                        space_count <= 3'b010;
                        near_slot <= 2'b10;
                        door_open_exit <= 1'b1;
                    end
                end
            end
            s12: 
            begin
                door_open <= 1'b0;
                door_open_exit = 1'b0;
                if (car_in) 
                begin
                    state <= s13;
                    space_count <= 3'b001;
                    near_slot <= 2'b01;
                    door_open <= 1'b1;
                end else if (car_out[2]) 
                begin
                    if (car_out[1:0] == 2'b10) 
                    begin
                        state <= s8;
                        space_count <= 3'b011;
                        near_slot <= 2'b00;
                        door_open_exit <= 1'b1;
                    end else if (car_out[1:0] == 2'b11) 
                    begin
                        state <= s4;
                        space_count <= 3'b011;
                        near_slot <= 2'b00;
                        door_open_exit <= 1'b1;
                    end
                end
            end
            s13: 
            begin
                door_open <= 1'b0;
                door_open_exit = 1'b0;
                if (car_in) 
                begin
                    state <= full;
                    space_count <= 3'b000;
                    full_garage <= 1'b1;   // be carefull
                    door_open <= 1'b1;
                end else if (car_out[2]) 
                begin
                    if (car_out[1:0] == 2'b00) 
                    begin
                        state <= s12;
                        space_count <= 3'b010;
                        near_slot <= 2'b00;
                        door_open_exit <= 1'b1;
                    end else if (car_out[1:0] == 2'b10) 
                    begin
                        state <= s9;
                        space_count <= 3'b010;
                        near_slot <= 2'b01;
                        door_open_exit <= 1'b1;
                    end else if (car_out[1:0] == 2'b11) 
                    begin
                        state <= s5;
                        space_count <= 3'b010; //be carefull
                        near_slot <= 2'b01;
                        door_open_exit <= 1'b1;
                    end
                end
            end
            s14: 
            begin
                door_open <= 1'b0;
                door_open_exit = 1'b0;
                if (car_in) 
                begin
                    state <= full;
                    space_count <= 3'b000;
                    full_garage <= 1'b1;
                    door_open <= 1'b1;
                end else if (car_out[2]) 
                begin
                    if (car_out[1:0] == 2'b10) 
                    begin
                        state <= s10;
                        space_count <= 3'b010;
                        near_slot <= 2'b00;
                        door_open_exit <= 1'b1;
                    end else if (car_out[1:0] == 2'b01) 
                    begin
                        state <= s12;
                        space_count <= 3'b010;
                        near_slot <= 2'b01;
                        door_open_exit <= 1'b1;
                    end else if (car_out[1:0] == 2'b11) 
                    begin
                        state <= s6;
                        space_count <= 3'b010;
                        near_slot <= 2'b00;
                        door_open_exit <= 1'b1;
                    end
                end
            end
            full: 
            begin
                door_open <= 1'b0;
                door_open_exit = 1'b0;
                if (car_in)
                begin
                    full_garage <= 1'b1;
                end else 
                begin
                    full_garage <= 1'b0;
                end
                if (car_out[2]) 
                begin
                    if (car_out[1:0] == 2'b00) 
                    begin
                        state <= s14;
                        space_count <= 3'b001;
                        near_slot <= 2'b00;
                        door_open_exit <= 1'b1;
                        full_garage <= 1'b0;
                    end else if (car_out[1:0] == 2'b01) 
                    begin
                        state <= s13;
                        space_count <= 3'b001;
                        near_slot <= 2'b01;
                        door_open_exit <= 1'b1;
                        full_garage <= 1'b0;
                    end else if (car_out[1:0] == 2'b10) 
                    begin
                        state <= s11;
                        space_count <= 3'b001;
                        near_slot <= 2'b10;
                        door_open_exit <= 1'b1;
                        full_garage <= 1'b0;
                    end else if (car_out[1:0] == 2'b11) 
                    begin
                        state <= s7;
                        space_count <= 3'b001;
                        near_slot <= 2'b11;
                        door_open_exit <= 1'b1;
                        full_garage <= 1'b0;
                    end
                end
            end
        endcase
    end
endmodule


`timescale 1ns/1ps

module FSM_tb;

    // Inputs
    reg car_in;
    reg [2:0] car_out;
    reg clk;
    reg rst;

    // Outputs
    wire [2:0] space_count;
    wire [1:0] near_slot;
    wire door_open;
    wire door_open_exit;
    wire full_garage;
    wire [3:0] state;

    // Instantiate the FSM module
    FSM uut (
        .car_in(car_in),
        .car_out(car_out),
        .clk(clk),
        .rst(rst),
        .space_count(space_count),
        .near_slot(near_slot),
        .door_open(door_open),
        .door_open_exit(door_open_exit),
        .full_garage(full_garage),
        .state(state)
    );

    // Clock generation
    initial begin
        clk = 0;
        forever #12.5 clk = ~clk;
    end
    
    integer input_file, output_file, scan_file;
    reg [3:0] input_data;

    initial begin
        $dumpfile("FSM_tb.vcd");
        $dumpvars(0, FSM_tb);

        car_in = 0;
        car_out = 3'b000;
        rst = 1;
        #25;
        rst = 0;
        #12.5


        input_file = $fopen("input.txt", "r");
        output_file = $fopen("output.txt", "w");

        if (input_file == 0 || output_file == 0) begin
            $display("Failed to open file.");
            $finish;
        end

        while (!$feof(input_file)) begin
            scan_file = $fscanf(input_file, "%4b\n", input_data);
            car_in = input_data[3];
            car_out = input_data[2:0];
            $display("Read input: car_in=%b, car_out=%b", car_in, car_out); 
            #25;
            if (space_count == 0) 
            begin
                $fwrite(output_file, "%4b [%d,-]\t", state, space_count);
            end else
            begin
                $fwrite(output_file, "%4b [%d,%d]\t", state, space_count, near_slot);
            end
            if (door_open | door_open_exit) begin
                $fwrite(output_file, "Door");
            end else if (full_garage) begin
                $fwrite(output_file, "Full");
            end
            $fwrite(output_file, "\n");
        end

        $fclose(input_file);
        $fclose(output_file);
        $finish;



    end

endmodule



        //         // Initialize Inputs
        // rst = 1'b1; #25
        // rst = 1'b0;

        // car_in = 0;
        // car_out = 3'b000; #30

        // // Test case 1: Add a car
        // car_in = 1; #25
        // car_in = 0; #30

        // // Test case 2: Add another car
        // car_in = 1; #25
        // car_in = 0; #30

        // // Test case 3: Remove a car from slot 0
        // car_out = 3'b100; #25 
        // car_out = 3'b000; #30

        // // Test case 4: Add another car
        // car_in = 1; #25
        // car_in = 0; #30

        // // Test case 5: Remove a car from slot 1
        // car_out = 3'b101; #25
        // car_out = 3'b000; #30

        // // Test case 6: Fill the garage
        // car_in = 1; #200
        // car_in = 0; #30

        // // Test case 7: Remove a car from slot 3
        // car_out = 3'b111; #25
        // car_out = 3'b000; #30
        // // Finish simulation
        // #50
        // $finish;

FSM_tb.vcd
$date
	Mon Dec 23 21:28:11 2024
$end
$version
	Icarus Verilog
$end
$timescale
	1ps
$end
$scope module FSM_tb $end
$var wire 4 ! state [3:0] $end
$var wire 3 " space_count [2:0] $end
$var wire 2 # near_slot [1:0] $end
$var wire 1 $ full_garage $end
$var wire 1 % door_open_exit $end
$var wire 1 & door_open $end
$var reg 1 ' car_in $end
$var reg 3 ( car_out [2:0] $end
$var reg 1 ) clk $end
$var reg 4 * input_data [3:0] $end
$var reg 1 + rst $end
$var integer 32 , input_file [31:0] $end
$var integer 32 - output_file [31:0] $end
$var integer 32 . scan_file [31:0] $end
$scope module uut $end
$var wire 1 ' car_in $end
$var wire 3 / car_out [2:0] $end
$var wire 1 ) clk $end
$var wire 1 + rst $end
$var parameter 4 0 empty $end
$var parameter 4 1 full $end
$var parameter 4 2 s1 $end
$var parameter 4 3 s10 $end
$var parameter 4 4 s11 $end
$var parameter 4 5 s12 $end
$var parameter 4 6 s13 $end
$var parameter 4 7 s14 $end
$var parameter 4 8 s2 $end
$var parameter 4 9 s3 $end
$var parameter 4 : s4 $end
$var parameter 4 ; s5 $end
$var parameter 4 < s6 $end
$var parameter 4 = s7 $end
$var parameter 4 > s8 $end
$var parameter 4 ? s9 $end
$var reg 1 & door_open $end
$var reg 1 % door_open_exit $end
$var reg 1 $ full_garage $end
$var reg 2 @ near_slot [1:0] $end
$var reg 3 A space_count [2:0] $end
$var reg 4 B state [3:0] $end
$upscope $end
$upscope $end
$enddefinitions $end
$comment Show the parameter values. $end
$dumpall
b1001 ?
b1000 >
b111 =
b110 <
b101 ;
b100 :
b11 9
b10 8
b1110 7
b1101 6
b1100 5
b1011 4
b1010 3
b1 2
b1111 1
b0 0
$end
#0
$dumpvars
b0 B
b100 A
b0 @
b0 /
bx .
bx -
bx ,
1+
bx *
0)
b0 (
0'
0&
0%
0$
b0 #
b100 "
b0 !
$end
#12500
1)
#25000
0)
0+
#37500
1)
b1 .
b0 *
b10000000000000000000000000000100 -
b10000000000000000000000000000011 ,
#50000
0)
#62500
b1 !
b1 B
1&
b1 #
b1 @
b11 "
b11 A
1)
1'
b1000 *
#75000
0)
#87500
b11 !
b11 B
b10 #
b10 @
b10 "
b10 A
1&
1)
b1 (
b1 /
b1001 *
#100000
0)
#112500
0&
1)
0'
b1 *
#125000
0)
#137500
1&
b11 #
b11 @
b1 "
b1 A
b111 !
b111 B
1)
b11 (
b11 /
1'
b1011 *
#150000
0)
#162500
1%
b1 #
b1 @
b10 "
b10 A
b101 !
b101 B
0&
1)
b101 (
b101 /
0'
b101 *
#175000
0)
#187500
1&
b11 #
b11 @
b1 "
b1 A
b111 !
b111 B
0%
1)
b0 (
b0 /
1'
b1000 *
#200000
0)
#212500
1%
b0 #
b0 @
b10 "
b10 A
b110 !
b110 B
0&
1)
b100 (
b100 /
0'
b100 *
#225000
0)
#237500
0%
1)
#250000
0)
#262500
1&
b11 #
b11 @
b1 "
b1 A
b111 !
b111 B
1)
b1 (
b1 /
1'
b1001 *
#275000
0)
#287500
1$
b0 "
b0 A
b1111 !
b1111 B
1&
1)
b0 (
b0 /
b1000 *
#300000
0)
#312500
0&
1)
b11 (
b11 /
b1011 *
#325000
0)
#337500
1)
b0 (
b0 /
b1000 *
#350000
0)
#362500
0$
1)
0'
b0 *
#375000
0)
#387500
1%
b0 #
b0 @
b1 "
b1 A
b1110 !
b1110 B
1)
b100 (
b100 /
b100 *
#400000
0)
#412500
0%
1)
b11 (
b11 /
b11 *
#425000
0)
#437500
1%
b10 "
b10 A
b1010 !
b1010 B
1)
b110 (
b110 /
b110 *
#450000
0)
#462500
b11 "
b11 A
b10 !
b10 B
1%
1)
b111 (
b111 /
b111 *
#475000
0)
#487500
b100 "
b100 A
b0 !
b0 B
1%
1)
b101 (
b101 /
b101 *
#500000
0)
#512500
0%
1)
b0 (
b0 /
b0 *
